calysto_hy/__init__.py
calysto_hy/__main__.py
calysto_hy/kernel.py
calysto_hy/version.py
calysto_hy-0.1.1.dist-info/DESCRIPTION.rst
calysto_hy-0.1.1.dist-info/LICENSE.txt
calysto_hy-0.1.1.dist-info/METADATA
calysto_hy-0.1.1.dist-info/RECORD
calysto_hy-0.1.1.dist-info/WHEEL
calysto_hy-0.1.1.dist-info/dependency_links.txt
calysto_hy-0.1.1.dist-info/metadata.json
calysto_hy-0.1.1.dist-info/top_level.txt
