Metadata-Version: 2.0
Name: calysto-hy
Version: 0.1.1
Summary: A Hy kernel for Jupyter based on MetaKernel
Home-page: https://github.com/Calysto/calysto_hy
Author: Douglas Blank
Author-email: doug.blank@gmail.com
License: UNKNOWN
Platform: UNKNOWN
Classifier: Framework :: IPython
Classifier: License :: OSI Approved :: BSD License
Classifier: Programming Language :: Python :: 3
Classifier: Programming Language :: Python :: 2
Classifier: Programming Language :: Lisp
Classifier: Topic :: System :: Shells
Requires-Dist: hy
Requires-Dist: metakernel
Requires-Dist: toolz
